pyvista_mypy_plugin/__init__.py
pyvista_mypy_plugin/mypy_plugin.py
pyvista_mypy_plugin-0.1.dist-info/LICENSE
pyvista_mypy_plugin-0.1.dist-info/METADATA
pyvista_mypy_plugin-0.1.dist-info/WHEEL
pyvista_mypy_plugin-0.1.dist-info/top_level.txt
pyvista_mypy_plugin-0.1.dist-info/RECORD
