Metadata-Version: 2.1
Name: pyvista-mypy-plugin
Version: 0.1
Summary: Mypy plugin for the PyVista project.
License: MIT
Project-URL: Homepage, https://github.com/pyvista/pyvista-mypy-plugin
Keywords: mypy,typing
Requires-Python: >=3.9
License-File: LICENSE
Requires-Dist: mypy
Requires-Dist: vtk
Requires-Dist: pyvista
Provides-Extra: dev
Requires-Dist: pytest; extra == "dev"
Requires-Dist: pytest-mypy-plugins; extra == "dev"
Requires-Dist: pre-commit; extra == "dev"
